sonicapi/__init__.py
sonicapi/__version__.py
sonicapi/sonicapi.py
sonicapi-0.2.5.dist-info/LICENSE
sonicapi-0.2.5.dist-info/METADATA
sonicapi-0.2.5.dist-info/WHEEL
sonicapi-0.2.5.dist-info/top_level.txt
sonicapi-0.2.5.dist-info/RECORD
