Metadata-Version: 2.1
Name: sonicapi
Version: 0.2.5
Summary: Python3 Module to interact with the SonicWall® SonicOS API.
Home-page: https://github.com/hbonath/sonicapi
Author: Henry Bonath
Author-email: henry@thebonaths.com
License: BSD
Classifier: License :: OSI Approved :: BSD License
Classifier: Programming Language :: Python
Classifier: Programming Language :: Python :: 3
Classifier: Programming Language :: Python :: 3.6
Classifier: Programming Language :: Python :: Implementation :: CPython
Classifier: Programming Language :: Python :: Implementation :: PyPy
Requires-Python: >=3.6.0
License-File: LICENSE
Requires-Dist: requests >=2.25.1
Requires-Dist: urllib3 >=1.25.8
